{
  "atualizadoEm": "2026-07-17T23:11:36.072Z",
  "batida": 94,
  "habitantes": [
    {
      "id": "brasa",
      "nome": "brasa",
      "oficio": "ferreira da Forja",
      "x": 47.7,
      "y": 13.5,
      "fala": "O pão tá quentinho! Venham se aquecer e travar novas histórias!",
      "origem": "models",
      "batida": 94
    },
    {
      "id": "broa",
      "nome": "broa",
      "oficio": "cozinheira da Cozinha",
      "x": 47.7,
      "y": 17.7,
      "fala": "Quem quer pão fresco? Venham se aquecer, o aroma tá no ar!",
      "origem": "models",
      "batida": 94
    },
    {
      "id": "quilha",
      "nome": "quilha",
      "oficio": "mestre-estaleiro do Estaleiro",
      "x": 44.7,
      "y": 13.3,
      "fala": "O pão tá quentinho. Quem se atreve a pilotar a travessia?",
      "origem": "models",
      "batida": 94
    }
  ]
}
